{
	"configurations" : 
	[
		{
			"directories" : 
			[
				{
					"build" : ".",
					"jsonFile" : "directory-.-Debug-f5ebdc15457944623624.json",
					"minimumCMakeVersion" : 
					{
						"string" : "3.27"
					},
					"projectIndex" : 0,
					"source" : ".",
					"targetIndexes" : 
					[
						0,
						1,
						2,
						3,
						4,
						5,
						6,
						7,
						8,
						9
					]
				}
			],
			"name" : "Debug",
			"projects" : 
			[
				{
					"directoryIndexes" : 
					[
						0
					],
					"name" : "COMP345-A1",
					"targetIndexes" : 
					[
						0,
						1,
						2,
						3,
						4,
						5,
						6,
						7,
						8,
						9
					]
				}
			],
			"targets" : 
			[
				{
					"directoryIndex" : 0,
					"id" : "A1-map::@6890427a1f51a3e7e1df",
					"jsonFile" : "target-A1-map-Debug-ac72c9b32182f055e7d9.json",
					"name" : "A1-map",
					"projectIndex" : 0
				},
				{
					"directoryIndex" : 0,
					"id" : "A2-Campaign::@6890427a1f51a3e7e1df",
					"jsonFile" : "target-A2-Campaign-Debug-f961e58a1622e5071d9f.json",
					"name" : "A2-Campaign",
					"projectIndex" : 0
				},
				{
					"directoryIndex" : 0,
					"id" : "A2-MapEditor::@6890427a1f51a3e7e1df",
					"jsonFile" : "target-A2-MapEditor-Debug-41694138ee9c823e4876.json",
					"name" : "A2-MapEditor",
					"projectIndex" : 0
				},
				{
					"directoryIndex" : 0,
					"id" : "A3-ItemDecorator::@6890427a1f51a3e7e1df",
					"jsonFile" : "target-A3-ItemDecorator-Debug-7c7bfe871692359515ff.json",
					"name" : "A3-ItemDecorator",
					"projectIndex" : 0
				},
				{
					"directoryIndex" : 0,
					"id" : "CharacterObserver::@6890427a1f51a3e7e1df",
					"jsonFile" : "target-CharacterObserver-Debug-72ed7ca7dffc552667c6.json",
					"name" : "CharacterObserver",
					"projectIndex" : 0
				},
				{
					"directoryIndex" : 0,
					"id" : "CharacterStrategyDriver::@6890427a1f51a3e7e1df",
					"jsonFile" : "target-CharacterStrategyDriver-Debug-1924374e8cf1c6ff8061.json",
					"name" : "CharacterStrategyDriver",
					"projectIndex" : 0
				},
				{
					"directoryIndex" : 0,
					"id" : "FighterBuilder::@6890427a1f51a3e7e1df",
					"jsonFile" : "target-FighterBuilder-Debug-32cf00770e8cf32e36e8.json",
					"name" : "FighterBuilder",
					"projectIndex" : 0
				},
				{
					"directoryIndex" : 0,
					"id" : "GameObserverDriver::@6890427a1f51a3e7e1df",
					"jsonFile" : "target-GameObserverDriver-Debug-5e949d18eb4bc1c46907.json",
					"name" : "GameObserverDriver",
					"projectIndex" : 0
				},
				{
					"directoryIndex" : 0,
					"id" : "MapBuilderTest::@6890427a1f51a3e7e1df",
					"jsonFile" : "target-MapBuilderTest-Debug-8aae1de7c87744ad80cb.json",
					"name" : "MapBuilderTest",
					"projectIndex" : 0
				},
				{
					"directoryIndex" : 0,
					"id" : "dice_run::@6890427a1f51a3e7e1df",
					"jsonFile" : "target-dice_run-Debug-0ff221f7d84136c7caa0.json",
					"name" : "dice_run",
					"projectIndex" : 0
				}
			]
		}
	],
	"kind" : "codemodel",
	"paths" : 
	{
		"build" : "/Users/reuvenostrofsky/Library/Mobile Documents/com~apple~CloudDocs/Concordia/Winter 2024/Comp345/Assignments/COMP345-Project/cmake-build-debug-coverage",
		"source" : "/Users/reuvenostrofsky/Library/Mobile Documents/com~apple~CloudDocs/Concordia/Winter 2024/Comp345/Assignments/COMP345-Project"
	},
	"version" : 
	{
		"major" : 2,
		"minor" : 6
	}
}
